{"en-us_component_affix.md":"1d747e4d","en-us_component_alert.md":"bff5e953","en-us_component_avatar.md":"e389a6e5","en-us_component_backtop.md":"5fce2725","en-us_component_badge.md":"63ad411e","en-us_component_border.md":"989d0f0b","en-us_component_breadcrumb.md":"90dc440e","en-us_component_button.md":"314b66b4","en-us_component_calendar.md":"799f7e4c","en-us_component_card.md":"2f989049","en-us_component_carousel.md":"a69d76ee","en-us_component_cascader.md":"071bde45","en-us_component_checkbox.md":"0d8d4f2a","en-us_component_collapse.md":"4d969f33","en-us_component_color-picker.md":"6f5cb5fc","en-us_component_color.md":"0a2c7024","en-us_component_config-provider.md":"9ddb43ac","en-us_component_container.md":"2160d1de","en-us_component_date-picker.md":"3460629c","en-us_component_datetime-picker.md":"77cc8b38","en-us_component_descriptions.md":"294bd0e9","en-us_component_dialog.md":"18463163","en-us_component_divider.md":"d0869d89","en-us_component_drawer.md":"c02fb7b9","en-us_component_dropdown.md":"431363c0","en-us_component_empty.md":"9a892809","en-us_component_form.md":"15323c7e","en-us_component_icon.md":"0f4e2ea4","en-us_component_image.md":"f9449def","en-us_component_infinite-scroll.md":"4a4b9956","en-us_component_input-number.md":"79e79837","en-us_component_input.md":"a23a8391","en-us_component_layout.md":"28184ca0","en-us_component_link.md":"dd0c0b38","en-us_component_loading.md":"80035cb5","en-us_component_menu.md":"70511d93","en-us_component_message-box.md":"15b0dc79","en-us_component_message.md":"01e69882","en-us_component_notification.md":"f06eb4ef","en-us_component_page-header.md":"8e753b5f","en-us_component_pagination.md":"5636a77b","en-us_component_popconfirm.md":"90796aa9","en-us_component_popover.md":"b12c1f67","en-us_component_progress.md":"b0a49d1b","en-us_component_radio.md":"fe646f54","en-us_component_rate.md":"9a30c00e","en-us_component_result.md":"9473ea68","en-us_component_scrollbar.md":"ba0223a4","en-us_component_select-v2.md":"56fab51c","en-us_component_select.md":"e485f4e9","en-us_component_skeleton.md":"2b6a5eb7","en-us_component_slider.md":"e6918f87","en-us_component_space.md":"30266bcf","en-us_component_steps.md":"b46befdc","en-us_component_switch.md":"284e201a","en-us_component_table-v2.md":"fcbffacf","en-us_component_table.md":"57e0d422","en-us_component_tabs.md":"58d45c75","en-us_component_tag.md":"47b247cb","en-us_component_time-picker.md":"4c501d75","en-us_component_time-select.md":"ff8a6c60","en-us_component_timeline.md":"146b4d56","en-us_component_tooltip-v2.md":"c9c6b562","en-us_component_tooltip.md":"a9a56d36","en-us_component_transfer.md":"f4d4fad8","en-us_component_tree-select.md":"bbdda553","en-us_component_tree-v2.md":"3e1cca50","en-us_component_tree.md":"85710508","en-us_component_typography.md":"5d1f8c8e","en-us_component_upload.md":"7f8e79e1","en-us_guide_changelog.md":"87be618e","en-us_guide_dark-mode.md":"db8a5d0e","en-us_guide_design.md":"c833c11e","en-us_guide_i18n.md":"ffd47ee8","en-us_guide_installation.md":"dd21f06e","en-us_guide_migration.md":"c3a3ffb2","en-us_guide_nav.md":"543224fe","en-us_guide_quickstart.md":"42b47f46","en-us_guide_theming.md":"13229314","en-us_guide_transitions.md":"29e67f38","en-us_index.md":"b1a04f43","en-us_resource_index.md":"7a0e8131","es-es_component_affix.md":"ea2d7328","es-es_component_alert.md":"5aa53582","es-es_component_avatar.md":"e5a5ea67","es-es_component_backtop.md":"c63ee1be","es-es_component_badge.md":"829b4054","es-es_component_border.md":"ad3798bb","es-es_component_breadcrumb.md":"a45cd649","es-es_component_button.md":"e9e7bf88","es-es_component_calendar.md":"2f5ea76e","es-es_component_card.md":"9cdf4116","es-es_component_carousel.md":"ca771c21","es-es_component_cascader.md":"6d04534c","es-es_component_checkbox.md":"97108b11","es-es_component_collapse.md":"bc155ba9","es-es_component_color-picker.md":"35ec4184","es-es_component_color.md":"16df6cfd","es-es_component_config-provider.md":"f632ec51","es-es_component_container.md":"ed76ab45","es-es_component_date-picker.md":"7858242f","es-es_component_datetime-picker.md":"42ab4cd6","es-es_component_descriptions.md":"ae886c99","es-es_component_dialog.md":"9b6a9303","es-es_component_divider.md":"54722a26","es-es_component_drawer.md":"d05eba3b","es-es_component_dropdown.md":"0ce78ba4","es-es_component_empty.md":"ed18d6ff","es-es_component_form.md":"c1774ba9","es-es_component_icon.md":"d8acf3be","es-es_component_image.md":"3e335c73","es-es_component_infinite-scroll.md":"aff0afda","es-es_component_input-number.md":"5daa24e0","es-es_component_input.md":"8d8719d0","es-es_component_layout.md":"85492687","es-es_component_link.md":"c61e313d","es-es_component_loading.md":"b16226f6","es-es_component_menu.md":"bc7d4f89","es-es_component_message-box.md":"2e166a88","es-es_component_message.md":"a8f1e9fe","es-es_component_notification.md":"2d031512","es-es_component_page-header.md":"3b93941f","es-es_component_pagination.md":"980c5c3a","es-es_component_popconfirm.md":"c0d6e027","es-es_component_popover.md":"40a94fe0","es-es_component_progress.md":"925d01fd","es-es_component_radio.md":"accdfcbd","es-es_component_rate.md":"fd49822c","es-es_component_result.md":"2fce6c44","es-es_component_scrollbar.md":"00501098","es-es_component_select-v2.md":"2f4e8936","es-es_component_select.md":"a0e3b591","es-es_component_skeleton.md":"bf42bd73","es-es_component_slider.md":"6843cb09","es-es_component_space.md":"a8e18d66","es-es_component_steps.md":"7b5e0ce0","es-es_component_switch.md":"84d2ce31","es-es_component_table-v2.md":"0a017aa4","es-es_component_table.md":"5c9100b0","es-es_component_tabs.md":"d076732f","es-es_component_tag.md":"c769d59a","es-es_component_time-picker.md":"2fb3f14a","es-es_component_time-select.md":"63c85e36","es-es_component_timeline.md":"df6fe4f3","es-es_component_tooltip-v2.md":"391fa064","es-es_component_tooltip.md":"b74faad7","es-es_component_transfer.md":"693d2e63","es-es_component_tree-select.md":"dfaea165","es-es_component_tree-v2.md":"bc1c3543","es-es_component_tree.md":"ca6b014f","es-es_component_typography.md":"15b612e2","es-es_component_upload.md":"af31c15a","es-es_guide_changelog.md":"93404a71","es-es_guide_dark-mode.md":"d61a6bbd","es-es_guide_design.md":"6bba6e74","es-es_guide_i18n.md":"071e0d49","es-es_guide_installation.md":"9f04f429","es-es_guide_migration.md":"0c06168f","es-es_guide_nav.md":"a88291a3","es-es_guide_quickstart.md":"8b53f25f","es-es_guide_theming.md":"eb2adeb2","es-es_guide_transitions.md":"6cf0d1bd","es-es_index.md":"28c6d31b","es-es_resource_index.md":"b5df2f17","index.md":"e1c72e2a"}
