{"en-us_component_affix.md":"BKX-uJdo","en-us_component_alert.md":"wc6TfxYM","en-us_component_anchor.md":"Ba8Cx3j_","en-us_component_avatar.md":"s74gzv_Z","en-us_component_backtop.md":"Cpa0fWYM","en-us_component_card.md":"BlU9wu4w","en-us_component_breadcrumb.md":"DQi8OP-i","en-us_component_calendar.md":"B_zBjGCs","en-us_component_border.md":"CQZa90fu","en-us_component_carousel.md":"Be6gy6or","en-us_component_color.md":"C3wFOx5H","en-us_component_button.md":"lH4qCWev","en-us_component_color-picker-panel.md":"DYLiYzGK","en-us_component_badge.md":"BsZHjTZw","en-us_component_collapse.md":"Do0wwtRL","en-us_component_color-picker.md":"CzZ2QKIx","en-us_component_date-picker-panel.md":"wieFVynM","en-us_component_checkbox.md":"Dsh6w92l","en-us_component_autocomplete.md":"DU8dmfQ3","en-us_component_container.md":"SxB-j-Xy","en-us_component_config-provider.md":"BXn77L2Y","en-us_component_divider.md":"BiYFJ2HH","en-us_component_drawer.md":"fcAYc3tj","en-us_component_descriptions.md":"DE77-dc5","en-us_component_empty.md":"BThNRvGC","en-us_component_dropdown.md":"9pli3qvx","en-us_component_datetime-picker.md":"ctiGjZ7s","en-us_component_dialog.md":"_J5ME5h_","en-us_component_date-picker.md":"UoLek8X3","en-us_component_icon.md":"DaiYdVga","en-us_component_form.md":"CAot1Ty6","en-us_component_input-number.md":"CAypZ5i9","en-us_component_infinite-scroll.md":"BC6907xR","en-us_component_message-box.md":"C5I54feu","es-es_component_badge.md":"zTUo97Bd","es-es_component_border.md":"M0-dhdCH","en-us_component_image.md":"CaJSn2Sf","en-us_component_message.md":"WHJHTGQO","es-es_component_carousel.md":"DK2qsk9d","en-us_component_progress.md":"g-Xx3U46","es-es_component_color-picker-panel.md":"-uBlFtcw","es-es_component_color-picker.md":"DZXO3Wxs","es-es_component_color.md":"CLzfMFBB","es-es_component_checkbox.md":"BUU4g8E1","en-us_component_layout.md":"DFOXbhlC","es-es_component_date-picker-panel.md":"h9z25qqi","en-us_component_page-header.md":"C7R3flA_","en-us_component_input-tag.md":"CrkXGtEO","en-us_component_popover.md":"Ds0hjsDG","es-es_component_message.md":"Cm1QyqSW","es-es_component_backtop.md":"B1Mzt3yP","es-es_component_loading.md":"Crc71JTW","es-es_component_mention.md":"C3om2tXX","es-es_component_button.md":"wnDYvLeX","es-es_component_calendar.md":"COACF52o","en-us_component_notification.md":"CyNkM76s","es-es_component_card.md":"CuguzJTT","es-es_component_result.md":"O6SLB8XT","en-us_component_pagination.md":"C6mdqzDH","es-es_component_descriptions.md":"BnQdOHYd","es-es_component_dialog.md":"JlFGY6kX","es-es_component_divider.md":"BSuoQ81Q","es-es_component_drawer.md":"DpbhNihF","es-es_component_collapse.md":"4uNRGEqF","es-es_component_breadcrumb.md":"CDLFYsuI","en-us_component_link.md":"usRQdaH3","es-es_component_infinite-scroll.md":"NfK6BfF8","en-us_component_menu.md":"BX8ojjV1","en-us_component_select.md":"_AJKVWW1","es-es_component_tabs.md":"wLFiQoJe","es-es_component_scrollbar.md":"DXp9KTGJ","es-es_component_tag.md":"E8HQojxz","es-es_component_segmented.md":"CljKUYSu","es-es_component_text.md":"DWubS_fa","es-es_component_time-picker.md":"BwUtmU5w","es-es_component_input.md":"dOvodnud","es-es_component_tree-select.md":"zSSn5Rog","es-es_component_switch.md":"C0nOq2Ru","es-es_component_popover.md":"BPVGRisf","es-es_component_layout.md":"U_X6Q6iZ","es-es_component_date-picker.md":"xXWXDC_C","es-es_component_datetime-picker.md":"D3KwFHoZ","es-es_component_container.md":"BDCVlcAY","es-es_component_link.md":"BF6jqxn4","es-es_component_dropdown.md":"BiNohCv3","es-es_component_message-box.md":"CfV0OgI3","es-es_component_empty.md":"YxhOc5No","es-es_component_progress.md":"sl86Adf7","es-es_component_radio.md":"BlSzYT2i","en-us_component_text.md":"DKDy8lEB","es-es_component_rate.md":"DzoBLGVI","es-es_component_overview.md":"GCjUgcyC","es-es_component_page-header.md":"BzydRQCe","es-es_component_form.md":"DwOAOauC","es-es_component_popconfirm.md":"CJ-3gFSR","es-es_component_icon.md":"lfrKCrqt","es-es_component_notification.md":"CZlBn24d","en-us_component_input.md":"p_5cRRHF","en-us_component_overview.md":"CT0ct9TK","en-us_component_radio.md":"BR2Vig1A","en-us_component_rate.md":"KDtMrQYo","en-us_component_result.md":"C-vD0QzG","en-us_component_scrollbar.md":"DiOpLP6t","en-us_component_slider.md":"DvBl4x1U","en-us_component_space.md":"CUAFq8jB","en-us_component_splitter.md":"C_ns6vvO","en-us_component_statistic.md":"Ddd8g23U","en-us_component_steps.md":"DbUeedzh","en-us_component_switch.md":"CXJ88__J","en-us_component_tabs.md":"DVhxbRee","en-us_component_tag.md":"DzlY6bNI","en-us_component_time-picker.md":"hMYVOF4-","en-us_component_time-select.md":"BnbeqxRt","es-es_component_select-v2.md":"feRS5m1q","en-us_component_timeline.md":"Dr4STWla","es-es_component_menu.md":"VlWIOaGJ","en-us_component_tooltip.md":"BbyJaNQK","zh-cn_guide_theming.md":"V7o8M_RW","zh-cn_guide_transitions.md":"D2gApmf-","zh-cn_guide_translation.md":"Bm-8FOtk","zh-cn_index.md":"C6AZ4ue1","zh-cn_resource_index.md":"CFpKQm3I","en-us_component_transfer.md":"ORqUCw42","zh-cn_component_statistic.md":"Cv6uqXMx","en-us_guide_commit-examples.md":"DrINk4-T","en-us_guide_dark-mode.md":"DPiEuoZ0","en-us_guide_design.md":"CPPfa-Q5","en-us_guide_dev-faq.md":"CKMjLASg","en-us_resource_index.md":"CP9hpxGb","es-es_component_affix.md":"X07CUrsa","es-es_component_alert.md":"CWBfCzy6","es-es_component_anchor.md":"yfJqqK5P","es-es_component_autocomplete.md":"DA6FHNgk","es-es_component_avatar.md":"B5bxh6pT","en-us_component_segmented.md":"C4iuLprm","zh-cn_component_icon.md":"CsgaxGuw","es-es_component_statistic.md":"DDZgw7wd","en-us_component_skeleton.md":"DfUW-RO2","en-us_guide_migration.md":"znIt2MQ3","en-us_component_tour.md":"ByfUDLOT","en-us_guide_quickstart.md":"HrAo01HA","en-us_guide_ssr.md":"DtWyhf7W","en-us_guide_transitions.md":"Bj9JgixQ","en-us_guide_translation.md":"CBhXp1gI","en-us_component_popconfirm.md":"CjNgtoDP","zh-cn_guide_ssr.md":"BAmQlzQr","zh-cn_component_splitter.md":"C3O0De7T","zh-cn_component_image.md":"BZaGRb_R","zh-cn_component_space.md":"CoXa-Uor","es-es_component_input-number.md":"CZoqxRfG","en-us_guide_namespace.md":"Dn9ZpRLC","en-us_guide_dev-guide.md":"C3hKAiKh","es-es_component_time-select.md":"CgkuLPJH","zh-cn_component_dropdown.md":"BUZ4BfzK","es-es_component_splitter.md":"BiPbbmIo","es-es_component_pagination.md":"BSsnXunO","en-us_guide_i18n.md":"CE9kgiFv","en-us_guide_nav.md":"Dxqa1gLU","en-us_guide_installation.md":"DA8uNzSX","zh-cn_component_select.md":"Bqav7RYU","zh-cn_component_form.md":"B5GuEvW5","es-es_component_table-v2.md":"Br4ef9vV","en-us_component_select-v2.md":"D_BBNo8S","zh-cn_component_infinite-scroll.md":"BYXIoLX8","zh-cn_component_skeleton.md":"CnCalWVL","zh-cn_component_input-number.md":"Bgzt8fKi","zh-cn_component_input-tag.md":"DoHCVTPw","zh-cn_component_input.md":"Drztsx-4","es-es_component_timeline.md":"DuOZuV_U","zh-cn_component_link.md":"C3s7Usrq","zh-cn_component_layout.md":"COVf16I1","en-us_component_mention.md":"CwyQfu0G","en-us_component_tree-select.md":"DG8E4RRA","zh-cn_component_mention.md":"Crt3-SrD","zh-cn_component_menu.md":"EsRIzY54","zh-cn_component_loading.md":"DLuFB_Uz","zh-cn_component_switch.md":"btA6xeUF","en-us_component_tree-v2.md":"ecjVkf_W","zh-cn_component_overview.md":"2WP8muLD","zh-cn_component_notification.md":"DzDfrqMG","zh-cn_guide_quickstart.md":"D_ILQV0Q","zh-cn_component_message.md":"DZy7mp6m","es-es_component_tour.md":"CPhpveIb","zh-cn_component_tag.md":"CD1eFgUR","zh-cn_component_message-box.md":"BqujcTG4","zh-cn_component_table-v2.md":"2h7XS5dO","es-es_component_table.md":"XuS1fFns","zh-cn_component_page-header.md":"Cdy6bygQ","zh-cn_component_tabs.md":"MuxGpJ55","es-es_component_cascader.md":"CCycrQME","zh-cn_component_tour.md":"D8-NE-Tn","zh-cn_component_table.md":"DH3cP9cK","zh-cn_component_tree-v2.md":"f6m_ZQz8","en-us_component_typography.md":"BJdMBEE0","zh-cn_component_pagination.md":"_9u9c7Tl","zh-cn_component_tree-select.md":"C0RsUTn1","en-us_component_tree.md":"HLe26qGJ","zh-cn_component_text.md":"DBoJrOGK","zh-cn_component_transfer.md":"Up_cIUmF","zh-cn_component_upload.md":"CL4s3yz8","zh-cn_component_time-picker.md":"BLTITjwT","zh-cn_guide_nav.md":"DXq5M3vU","zh-cn_guide_changelog.md":"DknPxd75","zh-cn_component_time-select.md":"C4TEgK-U","en-us_component_upload.md":"DzGx1nUC","es-es_component_transfer.md":"q2td4rKI","zh-cn_component_popconfirm.md":"CjwxkHHS","zh-cn_component_timeline.md":"Bb96EcJ5","zh-cn_component_tooltip.md":"3qSGTQnw","zh-cn_component_popover.md":"DIRwnZMp","zh-cn_component_rate.md":"C3ZKn0k4","zh-cn_component_typography.md":"sCDT1ouu","zh-cn_component_tree.md":"BnFYzqay","zh-cn_component_watermark.md":"B93b-KPY","zh-cn_component_scrollbar.md":"ClxHQ3oh","zh-cn_component_progress.md":"DFLFjhwV","zh-cn_guide_dark-mode.md":"BF8lR7WB","zh-cn_component_radio.md":"DzouV1rf","zh-cn_guide_commit-examples.md":"CH2Yhh_N","zh-cn_component_result.md":"QixAaIG0","zh-cn_guide_design.md":"7t26hpqL","zh-cn_component_select-v2.md":"V62172xO","en-us_component_watermark.md":"D3iyp68d","zh-cn_component_segmented.md":"C75nwDWm","es-es_guide_migration.md":"BhxuiErM","zh-cn_guide_dev-guide.md":"BRIzoKcY","zh-cn_guide_dev-faq.md":"B0COijwr","zh-cn_component_cascader.md":"CbJsqyut","es-es_component_image.md":"CnLes6yG","es-es_guide_nav.md":"BXJVZnUb","es-es_guide_ssr.md":"CQj6vAJ5","en-us_component_cascader.md":"DOKM2aIw","zh-cn_guide_installation.md":"DzFtFp4G","es-es_guide_theming.md":"Pwq7R3d8","zh-cn_component_steps.md":"Dq-lJzfb","zh-cn_guide_migration.md":"EcMX-xGe","es-es_component_input-tag.md":"BtpoNx7I","es-es_guide_namespace.md":"Ckx9FoR6","es-es_component_space.md":"DyTWqCWy","es-es_guide_quickstart.md":"xTH3iGNP","es-es_index.md":"DjkRKVG4","es-es_resource_index.md":"BpLwGrrx","zh-cn_component_alert.md":"Dz3G_6hr","zh-cn_component_anchor.md":"Dzf-9njU","es-es_component_skeleton.md":"DCC40Sb1","es-es_guide_transitions.md":"CwEogLK3","es-es_guide_translation.md":"DfqW9mHx","zh-cn_component_autocomplete.md":"BlhuNaOQ","index.md":"sBpMV6_B","zh-cn_component_affix.md":"DiLhKdct","zh-cn_component_avatar.md":"CrcgGsEC","en-us_component_loading.md":"B-cp86-M","zh-cn_component_backtop.md":"Dny0xi7h","zh-cn_component_breadcrumb.md":"BK77nci6","zh-cn_component_badge.md":"BG_zeCUx","zh-cn_component_border.md":"D-sanq3w","zh-cn_component_button.md":"BGKKedpI","zh-cn_component_calendar.md":"jgibVaG_","zh-cn_guide_namespace.md":"C6WjPr-C","zh-cn_guide_i18n.md":"B9865Mqz","zh-cn_component_color-picker-panel.md":"BexI-d9e","zh-cn_component_carousel.md":"VgKD68RN","zh-cn_component_color.md":"BzxBpAZZ","es-es_guide_dev-guide.md":"DYFgbwBR","es-es_guide_changelog.md":"BslF3bCc","es-es_guide_installation.md":"BVN2sC6O","es-es_guide_commit-examples.md":"DvxAEol5","zh-cn_component_card.md":"DCdRCmHF","es-es_component_select.md":"CFkR-71u","es-es_component_tree-v2.md":"CEfVjq6K","es-es_component_typography.md":"o-6ZUhuL","zh-cn_component_collapse.md":"DQy8p5Yl","es-es_component_upload.md":"Bqx13oUJ","es-es_guide_dark-mode.md":"DOjPlZKc","zh-cn_component_checkbox.md":"BYccQdyM","es-es_guide_design.md":"B7BhdElj","es-es_component_slider.md":"DpGz6P8p","en-us_index.md":"Cn_F7ADa","es-es_component_tree.md":"nQf9pvd1","zh-cn_component_date-picker-panel.md":"DVZiBRRG","es-es_guide_i18n.md":"DQfYJvlv","zh-cn_component_color-picker.md":"BJNNXmCZ","en-us_guide_changelog.md":"CUjw99_v","zh-cn_component_empty.md":"EEBaVbT-","es-es_guide_dev-faq.md":"D60m5Xti","zh-cn_component_config-provider.md":"CinEFUbU","zh-cn_component_datetime-picker.md":"Cp2zbA_5","es-es_component_watermark.md":"CcIveYvx","zh-cn_component_divider.md":"Bm8Yo7nN","zh-cn_component_date-picker.md":"BK8pKoXq","zh-cn_component_container.md":"BQsNVZCe","es-es_component_steps.md":"Drp0SK8T","es-es_component_config-provider.md":"C8Pb8W6Y","zh-cn_component_dialog.md":"DNuTpfa9","zh-cn_component_descriptions.md":"B5kwDC3H","zh-cn_component_drawer.md":"e4_ia8oD","en-us_guide_theming.md":"BqsjX942","es-es_component_tooltip.md":"Ded0FZCx","zh-cn_component_slider.md":"BEBJ1ynu","en-us_component_table.md":"BaNtzIsT","en-us_component_table-v2.md":"cLGrPtY4"}
