{"en-us_component_affix.md":"SSU-GyYi","en-us_component_alert.md":"DD6FBIPl","en-us_component_anchor.md":"CNYyPZNc","en-us_component_autocomplete.md":"Cg6Iv8zX","en-us_component_avatar.md":"q8KS8dwf","en-us_component_backtop.md":"DzulCqZZ","en-us_component_badge.md":"1OfwBvhV","en-us_component_border.md":"CPJY_a2d","en-us_component_breadcrumb.md":"uLTLdUHr","en-us_component_button.md":"CDBlCa5t","en-us_component_calendar.md":"CclcTODz","en-us_component_card.md":"CwT_sdHx","en-us_component_carousel.md":"C2gKTDDI","en-us_component_cascader.md":"B4ZXIlZz","en-us_component_checkbox.md":"MpMxJh-U","en-us_component_collapse.md":"Dwe0CRPH","en-us_component_color-picker-panel.md":"BBQ4pux4","en-us_component_color-picker.md":"D6wOizFa","en-us_component_color.md":"Dg39ZPo2","en-us_component_config-provider.md":"gFCbRfqb","en-us_component_container.md":"DHdDLmCT","en-us_component_date-picker-panel.md":"CJl2sqwB","en-us_component_date-picker.md":"InfXBP0s","en-us_component_datetime-picker.md":"iB7TzOp1","en-us_component_descriptions.md":"BDoqFCyC","en-us_component_dialog.md":"ILUTJPL8","en-us_component_divider.md":"CbM-Glrr","en-us_component_drawer.md":"BWiF9SH-","en-us_component_dropdown.md":"Cf2XoSke","en-us_component_empty.md":"mPTGZNHJ","en-us_component_form.md":"DLjcYWO-","en-us_component_icon.md":"ULSDFtBP","en-us_component_image.md":"BPu1tRft","en-us_component_infinite-scroll.md":"DWVit5lA","en-us_component_input-number.md":"BDy4N59g","en-us_component_input-otp.md":"DEeeg7yk","en-us_component_input-tag.md":"Zk2pj7YC","en-us_component_input.md":"C4H2IKEE","en-us_component_layout.md":"DLVWm6o4","en-us_component_link.md":"b725yST4","en-us_component_loading.md":"Do4cMMpa","en-us_component_mention.md":"B-rCQQjF","en-us_component_menu.md":"BcmbuX4J","en-us_component_message-box.md":"BdeXMnqn","en-us_component_message.md":"B8KrFkXm","en-us_component_notification.md":"CPlwpkrb","en-us_component_overview.md":"YCADgMSa","en-us_component_page-header.md":"C8uUGK3r","en-us_component_pagination.md":"DnwyhP43","en-us_component_popconfirm.md":"DQxcJssv","en-us_component_popover.md":"UpFRavlp","en-us_component_progress.md":"CDnlSunW","en-us_component_radio.md":"DhynHCN1","en-us_component_rate.md":"BHYr9n3L","en-us_component_result.md":"C8pgJrOz","en-us_component_scrollbar.md":"CyR7Gcmu","en-us_component_segmented.md":"Bua9oj_I","en-us_component_select-v2.md":"DGCKP_30","en-us_component_select.md":"TrDIDaC6","en-us_component_skeleton.md":"DKHeilcK","en-us_component_slider.md":"BtEOzvJr","en-us_component_space.md":"Cx0Wsqe5","en-us_component_splitter.md":"CHjUeqZd","en-us_component_statistic.md":"B8c4b_k8","en-us_component_steps.md":"DGNIn9jQ","en-us_component_switch.md":"B5Mt4_0z","en-us_component_table-v2.md":"CrD92hWs","en-us_component_table.md":"DoObqfIM","en-us_component_tabs.md":"D1n3KnXa","en-us_component_tag.md":"f9DxRkzN","en-us_component_text.md":"CSW8DUoP","en-us_component_time-picker.md":"C-tkK07b","en-us_component_time-select.md":"Nn-_aA2y","en-us_component_timeline.md":"DdWbvR0x","en-us_component_tooltip.md":"CkjP8l_F","en-us_component_tour.md":"CcaB0Owy","en-us_component_transfer.md":"CkvAgBmx","en-us_component_tree-select.md":"DkwSyKXu","en-us_component_tree-v2.md":"dKWhR6U1","en-us_component_tree.md":"ldjt64mW","en-us_component_typography.md":"Op5YdWXC","en-us_component_upload.md":"CVXC6VB6","en-us_component_watermark.md":"DYLwCUNK","en-us_guide_changelog.md":"CQgjRakU","en-us_guide_commit-examples.md":"BrAjCD7_","en-us_guide_custom-defaults.md":"BFUKyRp7","en-us_guide_dark-mode.md":"pU2sLSvI","en-us_guide_design.md":"D0KRxoPG","en-us_guide_dev-faq.md":"CYK-Ax5D","en-us_guide_dev-guide.md":"DrmZJ-2g","en-us_guide_i18n.md":"CjbojYBE","en-us_guide_installation.md":"Zb1PBVcC","en-us_guide_migration.md":"B12pcoxy","en-us_guide_namespace.md":"-0vcmXke","en-us_guide_nav.md":"HuwszP91","en-us_guide_quickstart.md":"BxLCaVAb","en-us_guide_ssr.md":"Df3UcMXO","en-us_guide_theming.md":"BDPQZKdu","en-us_guide_transitions.md":"HQ-kCTRU","en-us_guide_translation.md":"CX65x07o","en-us_index.md":"Dia6xOj9","en-us_resource_index.md":"8QfTlRRF","es-es_component_affix.md":"CR_x2ptA","es-es_component_alert.md":"Bszl4_lm","es-es_component_anchor.md":"DaLVTeu0","es-es_component_autocomplete.md":"DCsAZX-e","es-es_component_avatar.md":"BowvJMqL","es-es_component_backtop.md":"Bw1tlm6u","es-es_component_badge.md":"D6tstrQq","es-es_component_border.md":"DydqY8V7","es-es_component_breadcrumb.md":"Bbaq5npD","es-es_component_button.md":"BP0gcEGP","es-es_component_calendar.md":"DnOQsXqz","es-es_component_card.md":"tCA5LckG","es-es_component_carousel.md":"DJaiih5J","es-es_component_cascader.md":"DkBBPdgq","es-es_component_checkbox.md":"CWZKdyo9","es-es_component_collapse.md":"CSiFsc8I","es-es_component_color-picker-panel.md":"CURUNdHC","es-es_component_color-picker.md":"CvzA0lLY","es-es_component_color.md":"jiWRMjqS","es-es_component_config-provider.md":"C_IJ7e-5","es-es_component_container.md":"xP848XxU","es-es_component_date-picker-panel.md":"Bfe_P8Lg","es-es_component_date-picker.md":"CD34E-iI","es-es_component_datetime-picker.md":"Byzkhh4j","es-es_component_descriptions.md":"Z5qx9wRF","es-es_component_dialog.md":"CBo4exqZ","es-es_component_divider.md":"tcYxMa4b","es-es_component_drawer.md":"DN_NhofU","es-es_component_dropdown.md":"DqB1ffH-","es-es_component_empty.md":"DrsWQ6DV","es-es_component_form.md":"BcDvgCWs","es-es_component_icon.md":"CVY33BTJ","es-es_component_image.md":"DC9uWJzY","es-es_component_infinite-scroll.md":"BrFnCHeT","es-es_component_input-number.md":"WipsnzoM","es-es_component_input-otp.md":"D9UEmm9f","es-es_component_input-tag.md":"y0FHWsrZ","es-es_component_input.md":"-QHU_uJ1","es-es_component_layout.md":"5ihUB5MH","es-es_component_link.md":"5fQqUMux","es-es_component_loading.md":"bTSaXznf","es-es_component_mention.md":"rgZ_xN9p","es-es_component_menu.md":"CyZTjqHt","es-es_component_message-box.md":"Cu1vdYht","es-es_component_message.md":"BQnOE1LO","es-es_component_notification.md":"C60KCzQT","es-es_component_overview.md":"BdKdXseF","es-es_component_page-header.md":"CpiLUem4","es-es_component_pagination.md":"Bb6P3PMK","es-es_component_popconfirm.md":"3bYG74TF","es-es_component_popover.md":"Cte2a_7K","es-es_component_progress.md":"DSfresWo","es-es_component_radio.md":"oErjinNP","es-es_component_rate.md":"BtkmquW-","es-es_component_result.md":"D5Uo8e13","es-es_component_scrollbar.md":"B9gg_6fP","es-es_component_segmented.md":"DdpJYG7i","es-es_component_select-v2.md":"_Ap8q_s9","es-es_component_select.md":"oI7GQOTr","es-es_component_skeleton.md":"CYNaEFKq","es-es_component_slider.md":"BxZRtYua","es-es_component_space.md":"D7AwmVEs","es-es_component_splitter.md":"TOimcjyP","es-es_component_statistic.md":"VgXv-fF3","es-es_component_steps.md":"CKrlcrCC","es-es_component_switch.md":"DT9F5n3V","es-es_component_table-v2.md":"E6YNxC4Q","es-es_component_table.md":"BgM04LAE","es-es_component_tabs.md":"CQGuRXTH","es-es_component_tag.md":"gWjrw0Ww","es-es_component_text.md":"DMDfurx7","es-es_component_time-picker.md":"D47wrtt_","es-es_component_time-select.md":"Zs9pFntl","es-es_component_timeline.md":"ClvNgGj0","es-es_component_tooltip.md":"CoXXn4AH","es-es_component_tour.md":"DI1pBgO2","es-es_component_transfer.md":"Cv0aSCLK","es-es_component_tree-select.md":"CJ6SvDmr","es-es_component_tree-v2.md":"BWYoI-c_","es-es_component_tree.md":"DoRuUlhw","es-es_component_typography.md":"k7jYnRk4","es-es_component_upload.md":"DMEjOHxc","es-es_component_watermark.md":"B3m1PlkC","es-es_guide_changelog.md":"Dcc4Z1He","es-es_guide_commit-examples.md":"80X8wtrN","es-es_guide_custom-defaults.md":"DegQnMtD","es-es_guide_dark-mode.md":"CcXUyDIp","es-es_guide_design.md":"uwWHJVNe","es-es_guide_dev-faq.md":"syfTWOt9","es-es_guide_dev-guide.md":"3ju57An1","es-es_guide_i18n.md":"Y_269-2n","es-es_guide_installation.md":"B9XW_qjL","es-es_guide_migration.md":"twC0YHOY","es-es_guide_namespace.md":"CKSo8fNN","es-es_guide_nav.md":"BIztkyFW","es-es_guide_quickstart.md":"DKKuR_to","es-es_guide_ssr.md":"CZz00KuP","es-es_guide_theming.md":"DN_wzk7V","es-es_guide_transitions.md":"CzrrfUae","es-es_guide_translation.md":"DtAIe32u","es-es_index.md":"Cr4PP9sy","es-es_resource_index.md":"C_1rW5U7","index.md":"DIw50Gvv","zh-cn_component_affix.md":"C3CxpWA0","zh-cn_component_alert.md":"Dm7W7DhS","zh-cn_component_anchor.md":"Dk3c6t2n","zh-cn_component_autocomplete.md":"BhEKNmhP","zh-cn_component_avatar.md":"C0katshv","zh-cn_component_backtop.md":"CmLaaXDT","zh-cn_component_badge.md":"sMMI_4Qc","zh-cn_component_border.md":"CGmwnGfS","zh-cn_component_breadcrumb.md":"5C7BOmvj","zh-cn_component_button.md":"D0ljH2bH","zh-cn_component_calendar.md":"Bd4nSc3O","zh-cn_component_card.md":"DelfniOB","zh-cn_component_carousel.md":"Dxng-5WY","zh-cn_component_cascader.md":"01FkPwq7","zh-cn_component_checkbox.md":"CF8GBUN6","zh-cn_component_collapse.md":"CtGrKawP","zh-cn_component_color-picker-panel.md":"CaZhUicc","zh-cn_component_color-picker.md":"BODayLqs","zh-cn_component_color.md":"BVdVCm4i","zh-cn_component_config-provider.md":"B9G7bSIQ","zh-cn_component_container.md":"CwIE9zm3","zh-cn_component_date-picker-panel.md":"DcBMLd0D","zh-cn_component_date-picker.md":"BTXyw485","zh-cn_component_datetime-picker.md":"W7ZgMuMG","zh-cn_component_descriptions.md":"B_k-3zCn","zh-cn_component_dialog.md":"c2uHbgf3","zh-cn_component_divider.md":"B9vee-8P","zh-cn_component_drawer.md":"XR3JIPI_","zh-cn_component_dropdown.md":"DhuOTkz1","zh-cn_component_empty.md":"CD3Y5WDJ","zh-cn_component_form.md":"BGTC3dv6","zh-cn_component_icon.md":"C47on8kH","zh-cn_component_image.md":"zkgyQ20L","zh-cn_component_infinite-scroll.md":"DV7GaxcV","zh-cn_component_input-number.md":"BE-h7qCO","zh-cn_component_input-otp.md":"xrIfEiHg","zh-cn_component_input-tag.md":"DDUNvn5p","zh-cn_component_input.md":"DYrRfGlm","zh-cn_component_layout.md":"Bmjao9L3","zh-cn_component_link.md":"RT9r4m43","zh-cn_component_loading.md":"blZz5QSh","zh-cn_component_mention.md":"6B64bKp9","zh-cn_component_menu.md":"CfwLLdP7","zh-cn_component_message-box.md":"LfMRX5xX","zh-cn_component_message.md":"DRmO0b04","zh-cn_component_notification.md":"BBHKoiSh","zh-cn_component_overview.md":"D5vFCc8B","zh-cn_component_page-header.md":"xHvuMfMz","zh-cn_component_pagination.md":"D1TPj4TH","zh-cn_component_popconfirm.md":"DS7T17sP","zh-cn_component_popover.md":"DJZkd8ho","zh-cn_component_progress.md":"CjJUHUAm","zh-cn_component_radio.md":"C2wF1Sah","zh-cn_component_rate.md":"CAQOL_US","zh-cn_component_result.md":"D4Kfqgu4","zh-cn_component_scrollbar.md":"CqP3-5uc","zh-cn_component_segmented.md":"DDosiFpX","zh-cn_component_select-v2.md":"CmFBGQGY","zh-cn_component_select.md":"EKkRM7Jp","zh-cn_component_skeleton.md":"Bh5-aDuf","zh-cn_component_slider.md":"CS43xb1i","zh-cn_component_space.md":"BQETXJUG","zh-cn_component_splitter.md":"SsKOZMhU","zh-cn_component_statistic.md":"RDxDflcC","zh-cn_component_steps.md":"W0LXUAjF","zh-cn_component_switch.md":"Dl5y9WQ5","zh-cn_component_table-v2.md":"CnVlUMMo","zh-cn_component_table.md":"BhnBza8i","zh-cn_component_tabs.md":"CZSk8FvN","zh-cn_component_tag.md":"TCqMVU8R","zh-cn_component_text.md":"CoTOizHY","zh-cn_component_time-picker.md":"2ydy95GK","zh-cn_component_time-select.md":"xwJsOBAg","zh-cn_component_timeline.md":"-HKCkE4K","zh-cn_component_tooltip.md":"D9uk7gxZ","zh-cn_component_tour.md":"tZeH87rF","zh-cn_component_transfer.md":"Bn5A7FsY","zh-cn_component_tree-select.md":"j5K0Tqpm","zh-cn_component_tree-v2.md":"F8gLyBp8","zh-cn_component_tree.md":"CGb6NyQx","zh-cn_component_typography.md":"Dbga5kI0","zh-cn_component_upload.md":"Cp4-HstS","zh-cn_component_watermark.md":"DRmtI-wY","zh-cn_guide_changelog.md":"DC_GUoln","zh-cn_guide_commit-examples.md":"aEWhXaIH","zh-cn_guide_custom-defaults.md":"DRg4SLSf","zh-cn_guide_dark-mode.md":"CX0kEGr9","zh-cn_guide_design.md":"CAngebyy","zh-cn_guide_dev-faq.md":"B9g1htFq","zh-cn_guide_dev-guide.md":"Cooe0fmG","zh-cn_guide_i18n.md":"DfatJP2K","zh-cn_guide_installation.md":"Y20tBZmP","zh-cn_guide_migration.md":"BnGfseop","zh-cn_guide_namespace.md":"BppxkuIQ","zh-cn_guide_nav.md":"Cxu34W6s","zh-cn_guide_quickstart.md":"C0c_Q7K_","zh-cn_guide_ssr.md":"CybFIJ9i","zh-cn_guide_theming.md":"BDV9NNbe","zh-cn_guide_transitions.md":"DianLeCV","zh-cn_guide_translation.md":"xm3RZ3iB","zh-cn_index.md":"DL2dSBaQ","zh-cn_resource_index.md":"Ck8M8ij9"}
